collective.jsonify-1.6-py3.11-nspkg.pth
collective/jsonify/__init__.py
collective/jsonify/browser.py
collective/jsonify/configure.zcml
collective/jsonify/export.py
collective/jsonify/hook.py
collective/jsonify/methods.py
collective/jsonify/todo_i18nfolder.py
collective/jsonify/todo_localfs.py
collective/jsonify/todo_plone2.py
collective/jsonify/todo_plonearticle.py
collective/jsonify/todo_zphoto.py
collective/jsonify/wrapper.py
collective/jsonify/Extensions/json_methods.py
collective.jsonify-1.6.dist-info/METADATA
collective.jsonify-1.6.dist-info/WHEEL
collective.jsonify-1.6.dist-info/entry_points.txt
collective.jsonify-1.6.dist-info/namespace_packages.txt
collective.jsonify-1.6.dist-info/top_level.txt
collective.jsonify-1.6.dist-info/RECORD
