Metadata-Version: 2.1
Name: collective.jsonify
Version: 1.6
Summary: JSON representation for content in Plone from 2.0 and above
Home-page: https://github.com/collective/collective.jsonify
Author: Rok Garbas
Author-email: rok@garbas.si
License: GPL
Keywords: Plone content export json transmogrify
Classifier: Development Status :: 4 - Beta
Classifier: Framework :: Plone
Classifier: Framework :: Plone :: 4.3
Classifier: Programming Language :: Python
Classifier: Programming Language :: Python :: 2.4
Classifier: Programming Language :: Python :: 2.6
Classifier: Programming Language :: Python :: 2.7
Requires-Dist: setuptools
Provides-Extra: runhook
Requires-Dist: collective.runhook ; extra == 'runhook'
